README.rst
setup.cfg
setup.py
django_markdowner/__init__.py
django_markdowner/apps.py
django_markdowner/views.py
django_markdowner.egg-info/PKG-INFO
django_markdowner.egg-info/SOURCES.txt
django_markdowner.egg-info/dependency_links.txt
django_markdowner.egg-info/requires.txt
django_markdowner.egg-info/top_level.txt
tests/__init__.py
tests/conftest.py
tests/test_reads_markdown.py